AUTHORS
LICENSE
MANIFEST.in
README.rst
setup.py
solr_cli.py
solr_cli.egg-info/PKG-INFO
solr_cli.egg-info/SOURCES.txt
solr_cli.egg-info/dependency_links.txt
solr_cli.egg-info/entry_points.txt
solr_cli.egg-info/requires.txt
solr_cli.egg-info/top_level.txt