Metadata-Version: 1.0
Name: solr-cli
Version: 0.1
Summary: Command line client for Apache Solr
Home-page: http://github.com/moliware/solr_cli
Author: Miguel Olivares
Author-email: miguel@moliware.com
License: UNKNOWN
Platform: UNKNOWN
Classifier: Development Status :: 4 - Beta
Classifier: Intended Audience :: Developers
Classifier: License :: OSI Approved :: BSD License
Classifier: Natural Language :: English
Classifier: Operating System :: OS Independent
Classifier: Programming Language :: Python :: 2.7
Classifier: Programming Language :: Python
Classifier: Environment :: Console
